Testing_VS_code/__init__.py
Testing_VS_code/basic_code.py
Testing_VS_code/testing_basic_code.py
Testing_VS_code-0.1.dist-info/LICENCE.txt
Testing_VS_code-0.1.dist-info/METADATA
Testing_VS_code-0.1.dist-info/WHEEL
Testing_VS_code-0.1.dist-info/top_level.txt
Testing_VS_code-0.1.dist-info/RECORD
